readmemaker/__init__.py
readmemaker/my_module.py
readme_py_maker-0.1.7.dist-info/LICENSE
readme_py_maker-0.1.7.dist-info/METADATA
readme_py_maker-0.1.7.dist-info/WHEEL
readme_py_maker-0.1.7.dist-info/entry_points.txt
readme_py_maker-0.1.7.dist-info/top_level.txt
readme_py_maker-0.1.7.dist-info/RECORD
